pytest_depper/__init__.py
pytest_depper/analyzer.py
pytest_depper/cli.py
pytest_depper/git_utils.py
pytest_depper/plugin.py
pytest_depper/py.typed
pytest_depper-0.2.0.dist-info/licenses/LICENSE
pytest_depper-0.2.0.dist-info/METADATA
pytest_depper-0.2.0.dist-info/WHEEL
pytest_depper-0.2.0.dist-info/entry_points.txt
pytest_depper-0.2.0.dist-info/top_level.txt
pytest_depper-0.2.0.dist-info/RECORD
