Metadata-Version: 2.4
Name: pytest-depper
Version: 0.2.0
Summary: Smart test selection based on AST-level code dependency analysis
Author-email: Raymond Xu <raymond@example.com>
Maintainer-email: Raymond Xu <raymond@example.com>
License: MIT
Project-URL: Homepage, https://github.com/ryx2/pytest-depper
Project-URL: Documentation, https://github.com/ryx2/pytest-depper#readme
Project-URL: Repository, https://github.com/ryx2/pytest-depper
Project-URL: Issues, https://github.com/ryx2/pytest-depper/issues
Project-URL: Changelog, https://github.com/ryx2/pytest-depper/releases
Keywords: pytest,testing,dependencies,ast,test-selection,smart-testing,ci-cd
Classifier: Development Status :: 4 - Beta
Classifier: Framework :: Pytest
Classifier: Intended Audience :: Developers
Classifier: License :: OSI Approved :: MIT License
Classifier: Operating System :: OS Independent
Classifier: Programming Language :: Python
Classifier: Programming Language :: Python :: 3
Classifier: Programming Language :: Python :: 3.8
Classifier: Programming Language :: Python :: 3.9
Classifier: Programming Language :: Python :: 3.10
Classifier: Programming Language :: Python :: 3.11
Classifier: Programming Language :: Python :: 3.12
Classifier: Topic :: Software Development :: Testing
Classifier: Topic :: Software Development :: Testing :: Unit
Requires-Python: >=3.8
License-File: LICENSE
Requires-Dist: pytest>=7.0.0
Provides-Extra: dev
Requires-Dist: pytest>=7.0.0; extra == "dev"
Requires-Dist: pytest-cov>=4.0.0; extra == "dev"
Requires-Dist: ruff>=0.1.0; extra == "dev"
Requires-Dist: mypy>=1.0.0; extra == "dev"
Requires-Dist: black>=23.0.0; extra == "dev"
Dynamic: license-file
